odoo/addons/sale_product_returnable/README.rst
odoo/addons/sale_product_returnable/__init__.py
odoo/addons/sale_product_returnable/__manifest__.py
odoo/addons/sale_product_returnable/i18n/es.po
odoo/addons/sale_product_returnable/i18n/sale_product_returnable.pot
odoo/addons/sale_product_returnable/models/__init__.py
odoo/addons/sale_product_returnable/models/product_template.py
odoo/addons/sale_product_returnable/models/sale_order.py
odoo/addons/sale_product_returnable/readme/CONFIGURE.rst
odoo/addons/sale_product_returnable/readme/CONTRIBUTORS.rst
odoo/addons/sale_product_returnable/readme/DESCRIPTION.rst
odoo/addons/sale_product_returnable/static/description/icon.png
odoo/addons/sale_product_returnable/static/description/index.html
odoo/addons/sale_product_returnable/tests/__init__.py
odoo/addons/sale_product_returnable/tests/test_sale_product_returnable.py
odoo/addons/sale_product_returnable/views/product_template_view.xml
odoo12_addon_sale_product_returnable-12.0.1.0.2.dist-info/METADATA
odoo12_addon_sale_product_returnable-12.0.1.0.2.dist-info/WHEEL
odoo12_addon_sale_product_returnable-12.0.1.0.2.dist-info/top_level.txt
odoo12_addon_sale_product_returnable-12.0.1.0.2.dist-info/RECORD
